audrius_m_mod1_atsiskaitymas/__init__.py
audrius_m_mod1_atsiskaitymas/crawler.py
audrius_m_mod1_atsiskaitymas-0.1.0.dist-info/METADATA
audrius_m_mod1_atsiskaitymas-0.1.0.dist-info/WHEEL
audrius_m_mod1_atsiskaitymas-0.1.0.dist-info/top_level.txt
audrius_m_mod1_atsiskaitymas-0.1.0.dist-info/RECORD
