Metadata-Version: 2.1
Name: audrius-m-mod1-atsiskaitymas
Version: 0.1.0
Summary: Website crawler
Home-page: https://github.com/audriu/audrius-m-mod1-atsiskaitymas
Author: Audrius M
Author-email: balvakokay@gmail.com
Classifier: Programming Language :: Python :: 3
Classifier: License :: OSI Approved :: MIT License
Classifier: Operating System :: OS Independent
Requires-Python: >=3.10
Requires-Dist: requests ==2.32.3
Requires-Dist: requests-toolbelt ==1.0.0
Requires-Dist: bs4 ==0.0.2
